mlpro_int_river/__init__.py
mlpro_int_river/wrappers/__init__.py
mlpro_int_river/wrappers/basics.py
mlpro_int_river/wrappers/streams.py
mlpro_int_river/wrappers/clusteranalyzers/__init__.py
mlpro_int_river/wrappers/clusteranalyzers/basics.py
mlpro_int_river/wrappers/clusteranalyzers/clustream.py
mlpro_int_river/wrappers/clusteranalyzers/dbstream.py
mlpro_int_river/wrappers/clusteranalyzers/denstream.py
mlpro_int_river/wrappers/clusteranalyzers/kmeans.py
mlpro_int_river/wrappers/clusteranalyzers/streamkmeans.py
mlpro_int_river-0.5.0.dist-info/licenses/LICENSE
mlpro_int_river-0.5.0.dist-info/METADATA
mlpro_int_river-0.5.0.dist-info/WHEEL
mlpro_int_river-0.5.0.dist-info/top_level.txt
mlpro_int_river-0.5.0.dist-info/RECORD
