Metadata-Version: 2.4
Name: mlpro-int-river
Version: 0.5.0
Summary: MLPro: Integration River
Home-page: https://mlpro-int-river.readthedocs.io
Author: MLPro Team
Author-email: mlpro@listen.fh-swf.de
Project-URL: Bug Tracker, https://mlpro-int-river.readthedocs.io
Classifier: Programming Language :: Python :: 3
Classifier: License :: OSI Approved :: Apache Software License
Classifier: Operating System :: OS Independent
Requires-Python: >=3.11
License-File: LICENSE
Provides-Extra: full
Requires-Dist: mlpro[full]>=2.1.0; extra == "full"
Requires-Dist: river>=0.22.0; extra == "full"
Dynamic: license-file
